slidoc/__init__.py
slidoc/slidoc.py
slidoc-0.0.1.dist-info/AUTHORS.rst
slidoc-0.0.1.dist-info/LICENSE
slidoc-0.0.1.dist-info/METADATA
slidoc-0.0.1.dist-info/WHEEL
slidoc-0.0.1.dist-info/top_level.txt
slidoc-0.0.1.dist-info/RECORD
