Metadata-Version: 2.1
Name: slidoc
Version: 0.0.1
Summary: Use Python to make HTML slides via Pandoc.
Home-page: https://github.com/marskar/slidoc
Author: Martin Skarzynski
Author-email: marskar@gmail.com
License: MIT license
Keywords: slidoc
Platform: UNKNOWN
Classifier: Development Status :: 2 - Pre-Alpha
Classifier: Intended Audience :: Developers
Classifier: License :: OSI Approved :: MIT License
Classifier: Natural Language :: English
Classifier: Programming Language :: Python :: 2
Classifier: Programming Language :: Python :: 2.7
Classifier: Programming Language :: Python :: 3
Classifier: Programming Language :: Python :: 3.4
Classifier: Programming Language :: Python :: 3.5
Classifier: Programming Language :: Python :: 3.6
Classifier: Programming Language :: Python :: 3.7
